timeSeries_processing.py
timeSeries_processing-1.0.0.dist-info/LICENSE
timeSeries_processing-1.0.0.dist-info/METADATA
timeSeries_processing-1.0.0.dist-info/WHEEL
timeSeries_processing-1.0.0.dist-info/top_level.txt
timeSeries_processing-1.0.0.dist-info/RECORD
