Metadata-Version: 2.1
Name: timeSeries-processing
Version: 1.0.0
Summary: Library which processes time series datasets
Home-page: https://github.com/EnricoPittini/timeSeries-processing
Author: Enrico Pittini
Author-email: pittinienrico@hotmail.it
License: MIT
Platform: UNKNOWN
Classifier: Programming Language :: Python :: 3
Classifier: License :: OSI Approved :: MIT License
Classifier: Operating System :: OS Independent
License-File: LICENSE
Requires-Dist: matplotlib
Requires-Dist: pandas
Requires-Dist: sklearn
